pyxtal/XRD.py
pyxtal/XRD_indexer.py
pyxtal/__init__.py
pyxtal/block_crystal.py
pyxtal/constants.py
pyxtal/crystal.py
pyxtal/db.py
pyxtal/descriptor.py
pyxtal/elasticity.py
pyxtal/io.py
pyxtal/lattice.py
pyxtal/molecular_crystal.py
pyxtal/molecule.py
pyxtal/msg.py
pyxtal/operations.py
pyxtal/plane.py
pyxtal/reciprocal.py
pyxtal/representation.py
pyxtal/supergroup.py
pyxtal/symmetry.py
pyxtal/tolerance.py
pyxtal/util.py
pyxtal/version.py
pyxtal/viz.py
pyxtal/wyckoff_site.py
pyxtal/wyckoff_split.py
pyxtal/database/HM_Full.csv
pyxtal/database/__init__.py
pyxtal/database/atomic_scattering_params.json
pyxtal/database/bonds.json
pyxtal/database/bug.json
pyxtal/database/clusters.json
pyxtal/database/collection.py
pyxtal/database/element.py
pyxtal/database/k_subgroup.json
pyxtal/database/layer.csv
pyxtal/database/layer_generators.csv
pyxtal/database/layer_symmetry.csv
pyxtal/database/mech.db
pyxtal/database/molecules.json
pyxtal/database/point.csv
pyxtal/database/point_generators.csv
pyxtal/database/point_symmetry.csv
pyxtal/database/rod.csv
pyxtal/database/rod_generators.csv
pyxtal/database/rod_symmetry.csv
pyxtal/database/symbols.json
pyxtal/database/t_subgroup.json
pyxtal/database/test.db
pyxtal/database/wyckoff_generators.csv
pyxtal/database/wyckoff_list.csv
pyxtal/database/wyckoff_sets.json
pyxtal/database/wyckoff_symmetry.csv
pyxtal/database/cifs/0-G62.cif
pyxtal/database/cifs/1-G59.cif
pyxtal/database/cifs/191.vasp
pyxtal/database/cifs/2-G71.cif
pyxtal/database/cifs/3-G139.cif
pyxtal/database/cifs/4-G225.cif
pyxtal/database/cifs/ACBNZA01.cif
pyxtal/database/cifs/AXOSOW01.cif
pyxtal/database/cifs/Al2SiO5_mp-4753_symmetrized.cif
pyxtal/database/cifs/BTO-Amm2.cif
pyxtal/database/cifs/BTO.cif
pyxtal/database/cifs/FAU.cif
pyxtal/database/cifs/Fd3.cif
pyxtal/database/cifs/Fd3.vasp
pyxtal/database/cifs/Fd3m.cif
pyxtal/database/cifs/GUMMUW.cif
pyxtal/database/cifs/GeF2.cif
pyxtal/database/cifs/HAHCOI.cif
pyxtal/database/cifs/I41amd.vasp
pyxtal/database/cifs/I4_132.cif
pyxtal-1.1.2.dist-info/licenses/LICENSE.txt
pyxtal-1.1.2.dist-info/METADATA
pyxtal-1.1.2.dist-info/WHEEL
pyxtal-1.1.2.dist-info/top_level.txt
pyxtal-1.1.2.dist-info/RECORD
