Metadata-Version: 2.4
Name: pyxtal
Version: 1.1.2
Summary: Python code for generation of crystal structures based on symmetry constraints.
Home-page: https://github.com/MaterSim/PyXtal
Author: Scott Fredericks, Kevin Parrish, Qiang Zhu
Author-email: alecfans@gmail.com
License: MIT
Classifier: Programming Language :: Python :: 3
Classifier: License :: OSI Approved :: MIT License
Classifier: Operating System :: OS Independent
Requires-Python: >=3.9
License-File: LICENSE.txt
Requires-Dist: spglib>=2.5.0
Requires-Dist: pymatgen>=2024.3.1
Requires-Dist: pandas>=2.0.2
Requires-Dist: networkx>=2.3
Requires-Dist: ase>=3.23.0
Requires-Dist: scipy>=1.7.3
Requires-Dist: vasprun-xml>=1.0.4
Requires-Dist: importlib_metadata>=1.4
Requires-Dist: typing-extensions>=4.12
Requires-Dist: pyocse>=0.1.1
Requires-Dist: psutil
Provides-Extra: visualization
Requires-Dist: py3Dmol>=0.8.0; extra == "visualization"
Provides-Extra: descriptor
Requires-Dist: pyshtools>=4.10.3; extra == "descriptor"
Provides-Extra: molecules
Requires-Dist: openbabel; extra == "molecules"
Requires-Dist: pybel; extra == "molecules"
Provides-Extra: test
Requires-Dist: wheel; extra == "test"
Requires-Dist: pytest; extra == "test"
Requires-Dist: coverage; extra == "test"
Requires-Dist: pytest-cov; extra == "test"
Requires-Dist: monty>=2024.2.26; extra == "test"
Dynamic: author
Dynamic: author-email
Dynamic: classifier
Dynamic: description
Dynamic: description-content-type
Dynamic: home-page
Dynamic: license
Dynamic: license-file
Dynamic: provides-extra
Dynamic: requires-dist
Dynamic: requires-python
Dynamic: summary
